ofrestapi/__init__.py
ofrestapi/base.py
ofrestapi/exception.py
ofrestapi/groups.py
ofrestapi/messages.py
ofrestapi/muc.py
ofrestapi/sessions.py
ofrestapi/system.py
ofrestapi/users.py
ofrestapi/version.py
openfire_restapi-0.2.0.dist-info/DESCRIPTION.rst
openfire_restapi-0.2.0.dist-info/METADATA
openfire_restapi-0.2.0.dist-info/RECORD
openfire_restapi-0.2.0.dist-info/WHEEL
openfire_restapi-0.2.0.dist-info/metadata.json
openfire_restapi-0.2.0.dist-info/top_level.txt
